af/__init__.py
af/cli/__init__.py
af/cli/make_local.py
attachments_fetcher-0.1.3.dist-info/licenses/LICENSE
attachments_fetcher-0.1.3.dist-info/METADATA
attachments_fetcher-0.1.3.dist-info/WHEEL
attachments_fetcher-0.1.3.dist-info/entry_points.txt
attachments_fetcher-0.1.3.dist-info/top_level.txt
attachments_fetcher-0.1.3.dist-info/RECORD
