Metadata-Version: 2.4
Name: attachments-fetcher
Version: 0.1.3
Summary: A tool for downloading embedded images in a Markdown document into a dedicated directory and replacing the image links with the local ones.
Author-email: Dennis Sitelew <yowidin@gmail.com>
Project-URL: homepage, https://github.com/yowidin/attachments-fetcher
Project-URL: bugtrack, https://github.com/yowidin/attachments-fetcher/issues
Classifier: Programming Language :: Python :: 3
Classifier: License :: OSI Approved :: MIT License
Requires-Python: >=3.7
License-File: LICENSE
Requires-Dist: requests==2.31.0
Requires-Dist: urllib3==1.26.6
Provides-Extra: dev
Requires-Dist: pytest>=8.0; extra == "dev"
Dynamic: license-file
